{
  "todos": [
    {
      "id": "3762",
      "subject": "buy milk",
      "completed": false
    },
    {
      "id": "778e",
      "subject": "study k8s",
      "completed": false
    },
    {
      "id": "af9c",
      "subject": "1",
      "completed": false
    },
    {
      "id": "9d5d",
      "subject": "4",
      "completed": false
    },
    {
      "id": "56bf",
      "subject": "5",
      "completed": false
    },
    {
      "id": "d10d",
      "subject": "6",
      "completed": false
    },
    {
      "id": "7654",
      "subject": "7",
      "completed": false
    },
    {
      "id": "23c9",
      "subject": "8",
      "completed": false
    },
    {
      "id": "1500",
      "subject": "9",
      "completed": false
    },
    {
      "id": "5f73",
      "subject": "10",
      "completed": false
    },
    {
      "id": "18d6",
      "subject": "11",
      "completed": false
    },
    {
      "id": "159b",
      "subject": "12",
      "completed": false
    },
    {
      "id": "a475",
      "subject": "13",
      "completed": false
    },
    {
      "id": "c5c7",
      "subject": "14",
      "completed": false
    },
    {
      "id": "8e3a",
      "subject": "15",
      "completed": false
    },
    {
      "id": "609c",
      "subject": "16",
      "completed": false
    },
    {
      "id": "a51e",
      "subject": "17",
      "completed": false
    },
    {
      "id": "c45e",
      "subject": "18",
      "completed": false
    },
    {
      "id": "79e7",
      "subject": "19",
      "completed": false
    },
    {
      "id": "e27f",
      "subject": "20",
      "completed": false
    },
    {
      "id": "8439",
      "subject": "20",
      "completed": false
    },
    {
      "id": "8f07",
      "subject": "21",
      "completed": false
    },
    {
      "id": "e145",
      "subject": "22",
      "completed": false
    },
    {
      "id": "5b9c",
      "subject": "23",
      "completed": false
    },
    {
      "id": "043f",
      "subject": "24",
      "completed": false
    },
    {
      "id": "1c9e",
      "subject": "25",
      "completed": false
    },
    {
      "id": "1d76",
      "subject": "26",
      "completed": false
    },
    {
      "id": "d92b",
      "subject": "27",
      "completed": false
    },
    {
      "id": "4cc7",
      "subject": "28",
      "completed": false
    },
    {
      "id": "7bc3",
      "subject": "29",
      "completed": false
    },
    {
      "id": "df80",
      "subject": "30",
      "completed": false
    },
    {
      "id": "34ed",
      "subject": "a",
      "completed": false
    }
  ]
}